yesql/__init__.py
yesql/api.py
yesql/bin/__init__.py
yesql/core/__init__.py
yesql/core/drivers/__init__.py
yesql/core/drivers/base.py
yesql/core/drivers/postgresql/__init__.py
yesql/core/drivers/postgresql/_asyncpg.py
yesql/core/drivers/postgresql/_psycopg.py
yesql/core/middleware.py
yesql/core/parse.py
yesql/core/support.py
yesql/core/types.py
yesql/dynamic.py
yesql/repository.py
yesql/statement.py
yesql-0.1.1.dist-info/LICENSE.md
yesql-0.1.1.dist-info/WHEEL
yesql-0.1.1.dist-info/METADATA
yesql-0.1.1.dist-info/RECORD
